[
    {
        "id": 0,
        "title": "Task one",
        "description": "task number one",
        "done": false
    },
    {
        "id": 1,
        "title": "Task two",
        "description": "task number two",
        "done": false
    },
    {
        "id": 2,
        "title": "Task three",
        "description": "task number three",
        "done": false
    },
    {
        "id": 3,
        "title": "Task four",
        "description": "task number four",
        "done": true
    }
]